hanoikovoidcdau/__init__.py
hanoikovoidcdau/standardize.py
hanoikovoiduocdau-0.0.4.dist-info/METADATA
hanoikovoiduocdau-0.0.4.dist-info/WHEEL
hanoikovoiduocdau-0.0.4.dist-info/licenses/LICENSE
hanoikovoiduocdau-0.0.4.dist-info/RECORD
