Metadata-Version: 2.3
Name: hanoikovoiduocdau
Version: 0.0.4
Summary: A package for standardize Hanoi's address
Project-URL: Homepage, https://github.com/betty2310/hanoikovoiduocdau
Project-URL: Issues, https://github.com/betty2310/hanoikovoiduocdau/issues
Author-email: betty2310 <huynhduongsh1@gmail.com>
License-File: LICENSE
Classifier: License :: OSI Approved :: MIT License
Classifier: Operating System :: OS Independent
Classifier: Programming Language :: Python :: 3
Requires-Python: >=3.8
